mkwheelhouse.py
mkwheelhouse-1.1.0.dist-info/DESCRIPTION.rst
mkwheelhouse-1.1.0.dist-info/entry_points.txt
mkwheelhouse-1.1.0.dist-info/METADATA
mkwheelhouse-1.1.0.dist-info/metadata.json
mkwheelhouse-1.1.0.dist-info/RECORD
mkwheelhouse-1.1.0.dist-info/top_level.txt
mkwheelhouse-1.1.0.dist-info/WHEEL
