Metadata-Version: 2.0
Name: mkwheelhouse
Version: 1.1.0
Summary: Amazon S3 wheelhouse generator
Home-page: https://github.com/WhoopInc/mkwheelhouse
Author: Nikhil Benesch
Author-email: benesch@whoop.com
License: UNKNOWN
Platform: UNKNOWN
Classifier: License :: OSI Approved :: MIT License
Classifier: Development Status :: 4 - Beta
Classifier: Environment :: Console
Classifier: Intended Audience :: Developers
Classifier: Topic :: Software Development :: Build Tools
Requires-Dist: awscli (>=1.3.6)
Requires-Dist: boto (>=2.38.0)
Requires-Dist: yattag (>=0.9.2)
Requires-Dist: wheel (>=0.23.0)
Requires-Dist: pip (>=1.5.4)
Requires-Dist: six (>=1.9.0)
Provides-Extra: tests
Requires-Dist: pre-commit; extra == 'tests'
